xiaohei/__init__.py
xiaohei/aws/__init__.py
xiaohei/aws/artifactory.py
xiaohei/aws/bamboo.py
xiaohei/aws/cfstack.py
xiaohei/aws/jenkins.py
xiaohei/aws/nexus.py
xiaohei/aws/sonarqube.py
xiaohei/aws/s3/__init__.py
xiaohei/aws/s3/upload.py
xiaohei/azure/__init__.py
xiaohei-0.0.1.dist-info/LICENSE
xiaohei-0.0.1.dist-info/METADATA
xiaohei-0.0.1.dist-info/WHEEL
xiaohei-0.0.1.dist-info/top_level.txt
xiaohei-0.0.1.dist-info/RECORD
