Metadata-Version: 2.1
Name: xiaohei
Version: 0.0.1
Summary: UNKNOWN
Home-page: https://github.com/APAC-DevOps/xiaohei
Author: Jianhua Wu
Author-email: devops.apac@gmail.com
License: UNKNOWN
Platform: UNKNOWN
Classifier: Programming Language :: Python :: 3
Classifier: License :: OSI Approved :: MIT License
Classifier: Operating System :: OS Independent
Requires-Python: >=3.6
